iterwrapper/__init__.py
iterwrapper/misc.py
iterwrapper/wrapper.py
iterwrapper/data/__init__.py
iterwrapper/data/mutated.py
iterwrapper-0.1.4.dist-info/LICENSE
iterwrapper-0.1.4.dist-info/METADATA
iterwrapper-0.1.4.dist-info/WHEEL
iterwrapper-0.1.4.dist-info/top_level.txt
iterwrapper-0.1.4.dist-info/RECORD
