Metadata-Version: 2.1
Name: iterwrapper
Version: 0.1.4
Summary: A wrapper for FP style iterator manipulation
Home-page: https://github.com/Prunoideae/IterWrapper
Author: Prunoideae
Author-email: a455167189@163.com
License: UNKNOWN
Platform: UNKNOWN
Classifier: Programming Language :: Python :: 3
Classifier: License :: OSI Approved :: GNU General Public License v3 (GPLv3)
Classifier: Operating System :: OS Independent
Requires-Python: >=3.6
